canonicalwebteam/__init__.py
canonicalwebteam/exceptions.py
canonicalwebteam/retry_utils.py
canonicalwebteam/snap_recommendations.py
canonicalwebteam/store_api/__init__.py
canonicalwebteam/store_api/base.py
canonicalwebteam/store_api/dashboard.py
canonicalwebteam/store_api/devicegw.py
canonicalwebteam/store_api/publishergw.py
canonicalwebteam/stores_web_redis/__init__.py
canonicalwebteam/stores_web_redis/utility.py
canonicalwebteam_store_api-7.3.8.dist-info/METADATA
canonicalwebteam_store_api-7.3.8.dist-info/WHEEL
canonicalwebteam_store_api-7.3.8.dist-info/licenses/LICENSE
canonicalwebteam_store_api-7.3.8.dist-info/RECORD
