Metadata-Version: 2.4
Name: canonicalwebteam.store-api
Version: 7.3.8
Summary: 
License: LGPL-3.0
License-File: LICENSE
Author: Canonical Web Team
Author-email: webteam@canonical.com
Requires-Python: >=3.9,<4.0
Classifier: License :: OSI Approved :: GNU Lesser General Public License v3 (LGPLv3)
Classifier: Programming Language :: Python :: 3
Classifier: Programming Language :: Python :: 3.9
Classifier: Programming Language :: Python :: 3.10
Classifier: Programming Language :: Python :: 3.11
Classifier: Programming Language :: Python :: 3.12
Classifier: Programming Language :: Python :: 3.13
Classifier: Programming Language :: Python :: 3.14
Requires-Dist: cachetools (>=6.2.0,<7.0.0)
Requires-Dist: coverage (>=7.0,<8.0)
Requires-Dist: mypy (>=1.14.1,<2.0.0)
Requires-Dist: pymacaroons (==0.13.0)
Requires-Dist: redis (>=6.4.0,<7.0.0)
Requires-Dist: requests (>=2.32.2,<3.0.0)
